analysis/__init__.py
analysis/ai_analyzer.py
analysis/parser.py
analysis/pipeline_manager.py
analysis/static_scanner.py
cli/__init__.py
cli/config.py
cli/main.py
spoon_audit-0.1.0.dist-info/METADATA
spoon_audit-0.1.0.dist-info/WHEEL
spoon_audit-0.1.0.dist-info/entry_points.txt
spoon_audit-0.1.0.dist-info/top_level.txt
spoon_audit-0.1.0.dist-info/RECORD
