Metadata-Version: 2.4
Name: spoon-audit
Version: 0.1.0
Summary: AI-powered smart contract audit assistant with SpoonOS integration
Author-email: SecureAudit Collective <team@secureaudit.xyz>
License: MIT
Project-URL: Homepage, https://github.com/CodeKage25/spoon-audit
Project-URL: Bug Reports, https://github.com/CodeKage25/spoon-audit/issues
Project-URL: Source, https://github.com/CodeKage25/spoon-audit
Keywords: solidity,smart-contracts,audit,security,blockchain
Classifier: Development Status :: 3 - Alpha
Classifier: Intended Audience :: Developers
Classifier: Topic :: Software Development :: Quality Assurance
Classifier: Topic :: Security
Classifier: License :: OSI Approved :: MIT License
Classifier: Programming Language :: Python :: 3
Classifier: Programming Language :: Python :: 3.8
Classifier: Programming Language :: Python :: 3.9
Classifier: Programming Language :: Python :: 3.10
Classifier: Programming Language :: Python :: 3.11
Requires-Python: >=3.8
Requires-Dist: click>=8.0.0
Requires-Dist: rich>=13.0.0
Requires-Dist: requests>=2.28.0
Requires-Dist: watchdog>=2.1.0
Requires-Dist: python-dotenv>=1.0.0
Requires-Dist: py-solc-x>=1.12.0
Requires-Dist: typing-extensions<4.0.0,>=3.7.4
Requires-Dist: pydantic<1.10.0,>=1.8.0
Requires-Dist: slither-analyzer<0.10.0,>=0.8.0
Requires-Dist: openai<1.0.0,>=0.27.0
Provides-Extra: dev
Requires-Dist: pytest>=7.0.0; extra == "dev"
Requires-Dist: pytest-cov>=4.0.0; extra == "dev"
Requires-Dist: black>=23.0.0; extra == "dev"
Requires-Dist: flake8>=6.0.0; extra == "dev"
Requires-Dist: mypy>=1.0.0; extra == "dev"
Requires-Dist: pre-commit>=3.0.0; extra == "dev"
Provides-Extra: mythril
Requires-Dist: mythril==0.23.0; extra == "mythril"
